{
    "tempHash": "00B2EF154AF811DA",
    "tbluHash": "0051752AB36FF79D",
    "patch": [
        {
			"SubEntityOperation": [
				"6930d3c94ab28236",
				{
					"AddProperty": [
						"m_PosDualBackAttach",
						{
							"type": "SEntityTemplateReference",
							"value": "feed9989e4e0cd80"
						}
					]
				}
			]
		},
        {
            "AddEntity": [
                "feed9989e4e0cd80",
                {
                    "parent": "4a4dbb237cd7e08c",
                    "name": "Dual Back Attacher",
                    "factory": "[assembly:/_pro/design/gamecore/vrhelpers.template?/vrhelper_mirroredspatial.entitytemplate].pc_entitytype",
                    "blueprint": "[assembly:/_pro/design/gamecore/vrhelpers.template?/vrhelper_mirroredspatial.entitytemplate].pc_entityblueprint",
                    "properties": {
                        "m_rSpatial": {
                            "type": "SEntityTemplateReference",
                            "value": "3e59220365558eaa"
                        },
                        "m_eMirrorOperation1": {
                            "type": "EMirrorTransformOperation",
                            "value": "MTO_X_RotationNegate"
                        },
                        "m_eMirrorOperation2": {
                            "type": "EMirrorTransformOperation",
                            "value": "MTO_X_TranslationNegate"
                        },
                        "m_mOffset": {
                            "type": "SMatrix43",
                            "value": {
                                "rotation": {
                                    "x": -0.0,
                                    "y": 180.0,
                                    "z": -0.0
                                },
                                "position": {
                                    "x": 0.0,
                                    "y": 0.02500000037252903,
                                    "z": -0.1150000037252903
                                }
                            }
                        }
                    }
                }
            ]
        }
    ],
    "patchVersion": 6
}